cv_matcher/__init__.py
cv_matcher/ai_analyzer.py
cv_matcher/job_fetcher.py
cv_matcher/local_analyzer.py
cv_matcher/matcher.py
cv_matcher/models.py
cv_matcher/pdf_parser.py
cv_matcher/ui.py
cv_matcher-0.4.0.dist-info/METADATA
cv_matcher-0.4.0.dist-info/WHEEL
cv_matcher-0.4.0.dist-info/licenses/LICENSE
cv_matcher-0.4.0.dist-info/RECORD
