Metadata-Version: 2.4
Name: cv-matcher
Version: 0.4.0
Summary: AI-powered CV analysis and job matching library with web UI
Project-URL: Homepage, https://github.com/yourusername/cv-matcher
Project-URL: Documentation, https://github.com/yourusername/cv-matcher#readme
Project-URL: Repository, https://github.com/yourusername/cv-matcher
Project-URL: Issues, https://github.com/yourusername/cv-matcher/issues
Author-email: Your Name <your.email@example.com>
License: MIT
License-File: LICENSE
Keywords: ai,career,cv,job-matching,pdf,resume
Classifier: Development Status :: 3 - Alpha
Classifier: Intended Audience :: Developers
Classifier: License :: OSI Approved :: MIT License
Classifier: Programming Language :: Python :: 3
Classifier: Programming Language :: Python :: 3.9
Classifier: Programming Language :: Python :: 3.10
Classifier: Programming Language :: Python :: 3.11
Classifier: Programming Language :: Python :: 3.12
Classifier: Topic :: Software Development :: Libraries :: Python Modules
Classifier: Topic :: Text Processing :: General
Requires-Python: >=3.9
Requires-Dist: beautifulsoup4>=4.12.0
Requires-Dist: gradio>=4.0.0
Requires-Dist: openai>=1.0.0
Requires-Dist: pydantic>=2.0.0
Requires-Dist: pypdf>=3.17.0
Requires-Dist: python-dotenv>=1.0.0
Requires-Dist: requests>=2.31.0
Requires-Dist: rich>=13.0.0
Provides-Extra: dev
Requires-Dist: black>=23.0.0; extra == 'dev'
Requires-Dist: mypy>=1.5.0; extra == 'dev'
Requires-Dist: pytest-cov>=4.1.0; extra == 'dev'
Requires-Dist: pytest>=7.4.0; extra == 'dev'
Requires-Dist: ruff>=0.1.0; extra == 'dev'
Provides-Extra: flash-attn
Requires-Dist: flash-attn>=2.0.0; extra == 'flash-attn'
Provides-Extra: local
Requires-Dist: accelerate>=0.24.0; extra == 'local'
Requires-Dist: torch>=2.0.0; extra == 'local'
Requires-Dist: transformers>=4.35.0; extra == 'local'
